troop.py
troop-1.0.3.dist-info/METADATA
troop-1.0.3.dist-info/WHEEL
troop-1.0.3.dist-info/top_level.txt
troop-1.0.3.dist-info/RECORD
